README.txt
setup.py
periprocess/__init__.py
periprocess/process.py
periprocess.egg-info/PKG-INFO
periprocess.egg-info/SOURCES.txt
periprocess.egg-info/dependency_links.txt
periprocess.egg-info/entry_points.txt
periprocess.egg-info/not-zip-safe
periprocess.egg-info/top_level.txt