Metadata-Version: 1.0
Name: periprocess
Version: 0.0
Summary: subprocess front-end that keeps buffers of stdout/stderr
Home-page: http://k0s.org/hg/periprocess
Author: Jeff Hammel
Author-email: k0scist@gmail.com
License: MPL
Platform: UNKNOWN
